toolplot/__init__.py
toolplot/plot_create.py
toolplot/plot_fonts.py
toolplot/plot_save.py
toolplot/plot_setup.py
toolplot/plot_ticks.py
toolplot/plotly_utils.py
toolplot/py.typed
toolplot/special_plots/__init__.py
toolplot/special_plots/bar_plots.py
toolplot/special_plots/candlestick_plots.py
toolplot/special_plots/group_plots.py
toolplot/special_plots/log_histograms.py
toolplot/special_plots/two_dim_log_histogram.py
toolplot-0.3.7.dist-info/licenses/LICENSE
toolplot-0.3.7.dist-info/WHEEL
toolplot-0.3.7.dist-info/METADATA
toolplot-0.3.7.dist-info/RECORD
